[
	{
		"__TYPE__": "SharedSliceContent",
		"variation": "default",
		"primary": {
			"heading": {
				"__TYPE__": "StructuredTextContent",
				"value": [
					{
						"type": "heading2",
						"content": {
							"text": "Driver"
						}
					}
				]
			},
			"button_text": {
				"__TYPE__": "FieldContent",
				"value": "stopped",
				"type": "Text"
			},
			"button_link": {
				"__TYPE__": "LinkContent",
				"key": "a3ff9811-200a-4c76-9482-595ca5529146",
				"value": {
					"__TYPE__": "ExternalLink",
					"url": "http://google.com",
					"text": "no"
				}
			}
		},
		"items": []
	}
]